Metadata-Version: 2.1
Name: langchain-discord
Version: 0.0.20
Summary: A list of tools for LangChain to power Discord (Webhooks, etc.).
Home-page: https://github.com/0w9/langchain-discord
Download-URL: https://github.com/user/reponame/archive/v_01.tar.gz
Author: Lennard Dorst
Author-email: Lennard Dorst <lennardsolana@gmail.com>
License: MIT
Project-URL: Homepage, https://github.com/0w9/langchain-discord
Keywords: AI,LangChain,Discord
Classifier: Programming Language :: Python :: 3
Classifier: License :: OSI Approved :: MIT License
Classifier: Operating System :: OS Independent
Requires-Python: >=3.7
License-File: LICENSE.txt
